README.md
setup.cfg
setup.py
async_python_schema_registry_client.egg-info/PKG-INFO
async_python_schema_registry_client.egg-info/SOURCES.txt
async_python_schema_registry_client.egg-info/dependency_links.txt
async_python_schema_registry_client.egg-info/requires.txt
async_python_schema_registry_client.egg-info/top_level.txt
schema_registry/__init__.py
schema_registry/client/__init__.py
schema_registry/client/client.py
schema_registry/client/errors.py
schema_registry/client/paths.py
schema_registry/client/schema.py
schema_registry/client/status.py
schema_registry/client/urls.py
schema_registry/client/utils.py
schema_registry/serializers/__init__.py
schema_registry/serializers/errors.py
schema_registry/serializers/message_serializer.py
tests/client/__init__.py
tests/client/test_http_client.py
tests/client/test_schema.py
tests/client/test_schema_compatibility.py
tests/client/test_schema_delete.py
tests/client/test_schema_getters.py
tests/client/test_schema_registration.py
tests/client/test_schema_version.py
tests/client/test_urls.py
tests/serializer/__init__.py
tests/serializer/test_message_serializer.py