Metadata-Version: 2.1
Name: async-python-schema-registry-client
Version: 1.0.0
Summary: Asyn Python Rest Client to interact against Schema Registry Confluent Serverto manage Avro Schemas
Home-page: https://github.com/marcosschroh/async-python-schema-registry-client
Author: Marcos Schroh
Author-email: schrohm@gmail.com
License: MIT
Download-URL: https://pypi.org/project/async-python-schema-registry-client
Keywords: Schema Registry,Python,Async,Avro,Apache,Apache Avro
Platform: UNKNOWN
Classifier: Programming Language :: Python
Classifier: Programming Language :: Python :: 3
Classifier: Programming Language :: Python :: 3.6
Classifier: Programming Language :: Python :: 3.7
Classifier: Topic :: Software Development
